{
  "generated_at": "2026-07-17T21:42:36.733304+00:00",
  "run_count": 9,
  "total_containers": 35,
  "critical_count": 30,
  "warning_count": 0,
  "safe_count": 5,
  "total_penalty_usd": 343243.77,
  "avg_buffer_days": -79.7,
  "by_trade_lane": [
    {
      "trade_lane": "ASIA_EUR",
      "count": 8,
      "critical": 7,
      "total_burn": 101689.7
    },
    {
      "trade_lane": "INTRA_ASIA",
      "count": 7,
      "critical": 6,
      "total_burn": 64150.17
    },
    {
      "trade_lane": "TRANS_ATL",
      "count": 7,
      "critical": 5,
      "total_burn": 62305.12
    },
    {
      "trade_lane": "TRANS_PAC",
      "count": 13,
      "critical": 12,
      "total_burn": 115098.78
    }
  ],
  "by_lease_type": [
    {
      "lease_type": "Long-Term",
      "count": 9,
      "critical": 9
    },
    {
      "lease_type": "Master Lease",
      "count": 11,
      "critical": 8
    },
    {
      "lease_type": "One-Way",
      "count": 15,
      "critical": 13
    }
  ],
  "top_priority": [
    {
      "container_id": "APZU2035508",
      "lease_type": "Long-Term",
      "trade_lane_label": "Intra-Asia",
      "days_to_lfd": -74.24,
      "burn_rate_usd": 5810.84,
      "action_status": "Critical"
    },
    {
      "container_id": "BMOU7940572",
      "lease_type": "One-Way",
      "trade_lane_label": "Asia-Europe",
      "days_to_lfd": -86.24,
      "burn_rate_usd": 17432.52,
      "action_status": "Critical"
    },
    {
      "container_id": "CLHU9880624",
      "lease_type": "Long-Term",
      "trade_lane_label": "Trans-Pacific",
      "days_to_lfd": -120.24,
      "burn_rate_usd": 5839.21,
      "action_status": "Critical"
    },
    {
      "container_id": "UACU6836388",
      "lease_type": "Master Lease",
      "trade_lane_label": "Trans-Atlantic",
      "days_to_lfd": -108.24,
      "burn_rate_usd": 10007.56,
      "action_status": "Critical"
    },
    {
      "container_id": "CMAU6366286",
      "lease_type": "Master Lease",
      "trade_lane_label": "Trans-Atlantic",
      "days_to_lfd": -82.24,
      "burn_rate_usd": 10115.17,
      "action_status": "Critical"
    }
  ]
}